{
  "resourceType": "Bundle",
  "type": "transaction",
  "entry": [ {
    "fullUrl": "urn:uuid:d9af187e-147c-0613-c2eb-0ded1271436c",
    "resource": {
      "resourceType": "Patient",
      "id": "d9af187e-147c-0613-c2eb-0ded1271436c",
      "text": {
        "status": "generated",
        "div": "<div xmlns=\"http://www.w3.org/1999/xhtml\">Generated by <a href=\"https://github.com/synthetichealth/synthea\">Synthea</a>.Version identifier: master-branch-latest\n .   Person seed: -8152310404908497601  Population seed: 1612971958985</div>"
      },
      "extension": [ {
        "url": "http://hl7.org/fhir/StructureDefinition/patient-mothersMaidenName",
        "valueString": "Leeann571 Koepp521"
      }, {
        "url": "http://hl7.org/fhir/StructureDefinition/patient-birthPlace",
        "valueAddress": {
          "city": "Aberdeen",
          "state": "Aberdeenshire",
          "country": "GB"
        }
      }, {
        "url": "http://synthetichealth.github.io/synthea/disability-adjusted-life-years",
        "valueDecimal": 0.0
      }, {
        "url": "http://synthetichealth.github.io/synthea/quality-adjusted-life-years",
        "valueDecimal": 0.0
      } ],
      "identifier": [ {
        "system": "https://github.com/synthetichealth/synthea",
        "value": "d9af187e-147c-0613-c2eb-0ded1271436c"
      }, {
        "type": {
          "coding": [ {
            "system": "http://terminology.hl7.org/CodeSystem/v2-0203",
            "code": "MR",
            "display": "Medical Record Number"
          } ],
          "text": "Medical Record Number"
        },
        "system": "http://hospital.smarthealthit.org",
        "value": "d9af187e-147c-0613-c2eb-0ded1271436c"
      }, {
        "type": {
          "coding": [ {
            "system": "http://terminology.hl7.org/CodeSystem/v2-0203",
            "code": "SS",
            "display": "Social Security Number"
          } ],
          "text": "Social Security Number"
        },
        "system": "http://hl7.org/fhir/sid/us-ssn",
        "value": "999-75-6808"
      } ],
      "name": [ {
        "use": "official",
        "family": "Lemke654",
        "given": [ "Minda79" ]
      } ],
      "telecom": [ {
        "system": "phone",
        "value": "555-794-9805",
        "use": "home"
      } ],
      "gender": "female",
      "birthDate": "2020-10-19",
      "address": [ {
        "extension": [ {
          "url": "http://hl7.org/fhir/StructureDefinition/geolocation",
          "extension": [ {
            "url": "latitude",
            "valueDecimal": 57.23536934878314
          }, {
            "url": "longitude",
            "valueDecimal": -2.198937120399175
          } ]
        } ],
        "line": [ "269 Kuvalis Passage Unit 42" ],
        "city": "Aberdeen",
        "state": "Aberdeenshire",
        "postalCode": "AB10",
        "country": "GB"
      } ],
      "maritalStatus": {
        "coding": [ {
          "system": "http://terminology.hl7.org/CodeSystem/v3-MaritalStatus",
          "code": "S",
          "display": "Never Married"
        } ],
        "text": "Never Married"
      },
      "multipleBirthBoolean": false,
      "communication": [ {
        "language": {
          "coding": [ {
            "system": "urn:ietf:bcp:47",
            "code": "en-US",
            "display": "English"
          } ],
          "text": "English"
        }
      } ]
    },
    "request": {
      "method": "POST",
      "url": "Patient"
    }
  }, {
    "fullUrl": "urn:uuid:7bd929dd-e663-3d15-71f4-b1ca74ea6458",
    "resource": {
      "resourceType": "Encounter",
      "id": "7bd929dd-e663-3d15-71f4-b1ca74ea6458",
      "status": "finished",
      "class": {
        "system": "http://terminology.hl7.org/CodeSystem/v3-ActCode",
        "code": "AMB"
      },
      "type": [ {
        "coding": [ {
          "system": "http://snomed.info/sct",
          "code": "410620009",
          "display": "Well child visit (procedure)"
        } ],
        "text": "Well child visit (procedure)"
      } ],
      "subject": {
        "reference": "urn:uuid:d9af187e-147c-0613-c2eb-0ded1271436c",
        "display": "Minda79 Lemke654"
      },
      "participant": [ {
        "type": [ {
          "coding": [ {
            "system": "http://terminology.hl7.org/CodeSystem/v3-ParticipationType",
            "code": "PPRF",
            "display": "primary performer"
          } ],
          "text": "primary performer"
        } ],
        "period": {
          "start": "2020-10-19T08:24:41+02:00",
          "end": "2020-10-19T08:39:41+02:00"
        },
        "individual": {
          "reference": "Practitioner?identifier=http://hl7.org/fhir/sid/us-npi|9999999649",
          "display": "Dr. Alix578 Lynch190"
        }
      } ],
      "period": {
        "start": "2020-10-19T08:24:41+02:00",
        "end": "2020-10-19T08:39:41+02:00"
      },
      "serviceProvider": {
        "reference": "Organization?identifier=https://github.com/synthetichealth/synthea|5117b3d6-41d4-35d0-8b1f-4990d5b796b9",
        "display": "Woodend Hospital"
      }
    },
    "request": {
      "method": "POST",
      "url": "Encounter"
    }
  }, {
    "fullUrl": "urn:uuid:ff9a4a77-af42-0b49-8289-23b0dd869429",
    "resource": {
      "resourceType": "Immunization",
      "id": "ff9a4a77-af42-0b49-8289-23b0dd869429",
      "status": "completed",
      "vaccineCode": {
        "coding": [ {
          "system": "http://hl7.org/fhir/sid/cvx",
          "code": "08",
          "display": "Hep B, adolescent or pediatric"
        } ],
        "text": "Hep B, adolescent or pediatric"
      },
      "patient": {
        "reference": "urn:uuid:d9af187e-147c-0613-c2eb-0ded1271436c"
      },
      "encounter": {
        "reference": "urn:uuid:7bd929dd-e663-3d15-71f4-b1ca74ea6458"
      },
      "occurrenceDateTime": "2020-10-19T08:24:41+02:00",
      "primarySource": true
    },
    "request": {
      "method": "POST",
      "url": "Immunization"
    }
  }, {
    "fullUrl": "urn:uuid:d6696a33-4010-c8aa-f913-fc2ec993b7c5",
    "resource": {
      "resourceType": "Claim",
      "id": "d6696a33-4010-c8aa-f913-fc2ec993b7c5",
      "status": "active",
      "type": {
        "coding": [ {
          "system": "http://terminology.hl7.org/CodeSystem/claim-type",
          "code": "institutional"
        } ]
      },
      "use": "claim",
      "patient": {
        "reference": "urn:uuid:d9af187e-147c-0613-c2eb-0ded1271436c",
        "display": "Minda79 Lemke654"
      },
      "billablePeriod": {
        "start": "2020-10-19T08:24:41+02:00",
        "end": "2020-10-19T08:39:41+02:00"
      },
      "created": "2020-10-19T08:39:41+02:00",
      "provider": {
        "reference": "Organization?identifier=https://github.com/synthetichealth/synthea|5117b3d6-41d4-35d0-8b1f-4990d5b796b9",
        "display": "Woodend Hospital"
      },
      "priority": {
        "coding": [ {
          "system": "http://terminology.hl7.org/CodeSystem/processpriority",
          "code": "normal"
        } ]
      },
      "supportingInfo": [ {
        "sequence": 1,
        "category": {
          "coding": [ {
            "system": "http://terminology.hl7.org/CodeSystem/claiminformationcategory",
            "code": "info"
          } ]
        },
        "valueReference": {
          "reference": "urn:uuid:ff9a4a77-af42-0b49-8289-23b0dd869429"
        }
      } ],
      "insurance": [ {
        "sequence": 1,
        "focal": true,
        "coverage": {
          "display": "National Health Service"
        }
      } ],
      "item": [ {
        "sequence": 1,
        "productOrService": {
          "coding": [ {
            "system": "http://snomed.info/sct",
            "code": "410620009",
            "display": "Well child visit (procedure)"
          } ],
          "text": "Well child visit (procedure)"
        },
        "encounter": [ {
          "reference": "urn:uuid:7bd929dd-e663-3d15-71f4-b1ca74ea6458"
        } ]
      }, {
        "sequence": 2,
        "informationSequence": [ 1 ],
        "productOrService": {
          "coding": [ {
            "system": "http://hl7.org/fhir/sid/cvx",
            "code": "08",
            "display": "Hep B, adolescent or pediatric"
          } ],
          "text": "Hep B, adolescent or pediatric"
        },
        "net": {
          "value": 136.00,
          "currency": "USD"
        }
      } ],
      "total": {
        "value": 125.0,
        "currency": "USD"
      }
    },
    "request": {
      "method": "POST",
      "url": "Claim"
    }
  }, {
    "fullUrl": "urn:uuid:39d4b195-3ee3-4917-7e18-9ed7c163f8d0",
    "resource": {
      "resourceType": "ExplanationOfBenefit",
      "id": "39d4b195-3ee3-4917-7e18-9ed7c163f8d0",
      "contained": [ {
        "resourceType": "ServiceRequest",
        "id": "referral",
        "status": "completed",
        "intent": "order",
        "subject": {
          "reference": "urn:uuid:d9af187e-147c-0613-c2eb-0ded1271436c"
        },
        "requester": {
          "reference": "Practitioner?identifier=http://hl7.org/fhir/sid/us-npi|9999999649"
        },
        "performer": [ {
          "reference": "Practitioner?identifier=http://hl7.org/fhir/sid/us-npi|9999999649"
        } ]
      }, {
        "resourceType": "Coverage",
        "id": "coverage",
        "status": "active",
        "type": {
          "text": "National Health Service"
        },
        "beneficiary": {
          "reference": "urn:uuid:d9af187e-147c-0613-c2eb-0ded1271436c"
        },
        "payor": [ {
          "display": "National Health Service"
        } ]
      } ],
      "identifier": [ {
        "system": "https://bluebutton.cms.gov/resources/variables/clm_id",
        "value": "d6696a33-4010-c8aa-f913-fc2ec993b7c5"
      }, {
        "system": "https://bluebutton.cms.gov/resources/identifier/claim-group",
        "value": "99999999999"
      } ],
      "status": "active",
      "type": {
        "coding": [ {
          "system": "http://terminology.hl7.org/CodeSystem/claim-type",
          "code": "institutional"
        } ]
      },
      "use": "claim",
      "patient": {
        "reference": "urn:uuid:d9af187e-147c-0613-c2eb-0ded1271436c"
      },
      "billablePeriod": {
        "start": "2020-10-19T08:39:41+02:00",
        "end": "2021-10-19T08:39:41+02:00"
      },
      "created": "2020-10-19T08:39:41+02:00",
      "insurer": {
        "display": "National Health Service"
      },
      "provider": {
        "reference": "Practitioner?identifier=http://hl7.org/fhir/sid/us-npi|9999999649"
      },
      "referral": {
        "reference": "#referral"
      },
      "claim": {
        "reference": "urn:uuid:d6696a33-4010-c8aa-f913-fc2ec993b7c5"
      },
      "outcome": "complete",
      "careTeam": [ {
        "sequence": 1,
        "provider": {
          "reference": "Practitioner?identifier=http://hl7.org/fhir/sid/us-npi|9999999649"
        },
        "role": {
          "coding": [ {
            "system": "http://terminology.hl7.org/CodeSystem/claimcareteamrole",
            "code": "primary",
            "display": "Primary Care Practitioner"
          } ]
        }
      } ],
      "insurance": [ {
        "focal": true,
        "coverage": {
          "reference": "#coverage",
          "display": "National Health Service"
        }
      } ],
      "item": [ {
        "sequence": 1,
        "category": {
          "coding": [ {
            "system": "https://bluebutton.cms.gov/resources/variables/line_cms_type_srvc_cd",
            "code": "1",
            "display": "Medical care"
          } ]
        },
        "productOrService": {
          "coding": [ {
            "system": "http://snomed.info/sct",
            "code": "410620009",
            "display": "Well child visit (procedure)"
          } ],
          "text": "Well child visit (procedure)"
        },
        "servicedPeriod": {
          "start": "2020-10-19T08:24:41+02:00",
          "end": "2020-10-19T08:39:41+02:00"
        },
        "locationCodeableConcept": {
          "coding": [ {
            "system": "http://terminology.hl7.org/CodeSystem/ex-serviceplace",
            "code": "19",
            "display": "Off Campus-Outpatient Hospital"
          } ]
        },
        "encounter": [ {
          "reference": "urn:uuid:7bd929dd-e663-3d15-71f4-b1ca74ea6458"
        } ]
      }, {
        "sequence": 2,
        "informationSequence": [ 1 ],
        "category": {
          "coding": [ {
            "system": "https://bluebutton.cms.gov/resources/variables/line_cms_type_srvc_cd",
            "code": "1",
            "display": "Medical care"
          } ]
        },
        "productOrService": {
          "coding": [ {
            "system": "http://hl7.org/fhir/sid/cvx",
            "code": "08",
            "display": "Hep B, adolescent or pediatric"
          } ],
          "text": "Hep B, adolescent or pediatric"
        },
        "servicedPeriod": {
          "start": "2020-10-19T08:24:41+02:00",
          "end": "2020-10-19T08:39:41+02:00"
        },
        "locationCodeableConcept": {
          "coding": [ {
            "system": "http://terminology.hl7.org/CodeSystem/ex-serviceplace",
            "code": "19",
            "display": "Off Campus-Outpatient Hospital"
          } ]
        },
        "net": {
          "value": 136.00,
          "currency": "USD"
        },
        "adjudication": [ {
          "category": {
            "coding": [ {
              "system": "https://bluebutton.cms.gov/resources/codesystem/adjudication",
              "code": "https://bluebutton.cms.gov/resources/variables/line_coinsrnc_amt",
              "display": "Line Beneficiary Coinsurance Amount"
            } ]
          },
          "amount": {
            "value": 27.200000000000003,
            "currency": "USD"
          }
        }, {
          "category": {
            "coding": [ {
              "system": "https://bluebutton.cms.gov/resources/codesystem/adjudication",
              "code": "https://bluebutton.cms.gov/resources/variables/line_prvdr_pmt_amt",
              "display": "Line Provider Payment Amount"
            } ]
          },
          "amount": {
            "value": 108.80000000000001,
            "currency": "USD"
          }
        }, {
          "category": {
            "coding": [ {
              "system": "https://bluebutton.cms.gov/resources/codesystem/adjudication",
              "code": "https://bluebutton.cms.gov/resources/variables/line_sbmtd_chrg_amt",
              "display": "Line Submitted Charge Amount"
            } ]
          },
          "amount": {
            "value": 136.00,
            "currency": "USD"
          }
        }, {
          "category": {
            "coding": [ {
              "system": "https://bluebutton.cms.gov/resources/codesystem/adjudication",
              "code": "https://bluebutton.cms.gov/resources/variables/line_alowd_chrg_amt",
              "display": "Line Allowed Charge Amount"
            } ]
          },
          "amount": {
            "value": 136.00,
            "currency": "USD"
          }
        }, {
          "category": {
            "coding": [ {
              "system": "https://bluebutton.cms.gov/resources/codesystem/adjudication",
              "code": "https://bluebutton.cms.gov/resources/variables/line_bene_ptb_ddctbl_amt",
              "display": "Line Beneficiary Part B Deductible Amount"
            } ]
          },
          "amount": {
            "value": 0,
            "currency": "USD"
          }
        }, {
          "category": {
            "coding": [ {
              "system": "https://bluebutton.cms.gov/resources/codesystem/adjudication",
              "code": "https://bluebutton.cms.gov/resources/variables/line_prcsg_ind_cd",
              "display": "Line Processing Indicator Code"
            } ]
          }
        } ]
      } ],
      "total": [ {
        "category": {
          "coding": [ {
            "system": "http://terminology.hl7.org/CodeSystem/adjudication",
            "code": "submitted",
            "display": "Submitted Amount"
          } ],
          "text": "Submitted Amount"
        },
        "amount": {
          "value": 125.0,
          "currency": "USD"
        }
      } ],
      "payment": {
        "amount": {
          "value": 108.80000000000001,
          "currency": "USD"
        }
      }
    },
    "request": {
      "method": "POST",
      "url": "ExplanationOfBenefit"
    }
  }, {
    "fullUrl": "urn:uuid:fd0f4a40-24d2-87b3-5b4a-df1af3071cc8",
    "resource": {
      "resourceType": "Encounter",
      "id": "fd0f4a40-24d2-87b3-5b4a-df1af3071cc8",
      "status": "finished",
      "class": {
        "system": "http://terminology.hl7.org/CodeSystem/v3-ActCode",
        "code": "AMB"
      },
      "type": [ {
        "coding": [ {
          "system": "http://snomed.info/sct",
          "code": "410620009",
          "display": "Well child visit (procedure)"
        } ],
        "text": "Well child visit (procedure)"
      } ],
      "subject": {
        "reference": "urn:uuid:d9af187e-147c-0613-c2eb-0ded1271436c",
        "display": "Minda79 Lemke654"
      },
      "participant": [ {
        "type": [ {
          "coding": [ {
            "system": "http://terminology.hl7.org/CodeSystem/v3-ParticipationType",
            "code": "PPRF",
            "display": "primary performer"
          } ],
          "text": "primary performer"
        } ],
        "period": {
          "start": "2020-11-23T07:24:41+01:00",
          "end": "2020-11-23T07:39:41+01:00"
        },
        "individual": {
          "reference": "Practitioner?identifier=http://hl7.org/fhir/sid/us-npi|9999999649",
          "display": "Dr. Alix578 Lynch190"
        }
      } ],
      "period": {
        "start": "2020-11-23T07:24:41+01:00",
        "end": "2020-11-23T07:39:41+01:00"
      },
      "serviceProvider": {
        "reference": "Organization?identifier=https://github.com/synthetichealth/synthea|5117b3d6-41d4-35d0-8b1f-4990d5b796b9",
        "display": "Woodend Hospital"
      }
    },
    "request": {
      "method": "POST",
      "url": "Encounter"
    }
  }, {
    "fullUrl": "urn:uuid:0fc0cf3f-b4aa-f2a1-6c87-5ab9e83d4069",
    "resource": {
      "resourceType": "Immunization",
      "id": "0fc0cf3f-b4aa-f2a1-6c87-5ab9e83d4069",
      "status": "completed",
      "vaccineCode": {
        "coding": [ {
          "system": "http://hl7.org/fhir/sid/cvx",
          "code": "08",
          "display": "Hep B, adolescent or pediatric"
        } ],
        "text": "Hep B, adolescent or pediatric"
      },
      "patient": {
        "reference": "urn:uuid:d9af187e-147c-0613-c2eb-0ded1271436c"
      },
      "encounter": {
        "reference": "urn:uuid:fd0f4a40-24d2-87b3-5b4a-df1af3071cc8"
      },
      "occurrenceDateTime": "2020-11-23T07:24:41+01:00",
      "primarySource": true
    },
    "request": {
      "method": "POST",
      "url": "Immunization"
    }
  }, {
    "fullUrl": "urn:uuid:82eaeea3-ac4d-2f0f-c1d2-8775604f6552",
    "resource": {
      "resourceType": "Claim",
      "id": "82eaeea3-ac4d-2f0f-c1d2-8775604f6552",
      "status": "active",
      "type": {
        "coding": [ {
          "system": "http://terminology.hl7.org/CodeSystem/claim-type",
          "code": "institutional"
        } ]
      },
      "use": "claim",
      "patient": {
        "reference": "urn:uuid:d9af187e-147c-0613-c2eb-0ded1271436c",
        "display": "Minda79 Lemke654"
      },
      "billablePeriod": {
        "start": "2020-11-23T07:24:41+01:00",
        "end": "2020-11-23T07:39:41+01:00"
      },
      "created": "2020-11-23T07:39:41+01:00",
      "provider": {
        "reference": "Organization?identifier=https://github.com/synthetichealth/synthea|5117b3d6-41d4-35d0-8b1f-4990d5b796b9",
        "display": "Woodend Hospital"
      },
      "priority": {
        "coding": [ {
          "system": "http://terminology.hl7.org/CodeSystem/processpriority",
          "code": "normal"
        } ]
      },
      "supportingInfo": [ {
        "sequence": 1,
        "category": {
          "coding": [ {
            "system": "http://terminology.hl7.org/CodeSystem/claiminformationcategory",
            "code": "info"
          } ]
        },
        "valueReference": {
          "reference": "urn:uuid:0fc0cf3f-b4aa-f2a1-6c87-5ab9e83d4069"
        }
      } ],
      "insurance": [ {
        "sequence": 1,
        "focal": true,
        "coverage": {
          "display": "National Health Service"
        }
      } ],
      "item": [ {
        "sequence": 1,
        "productOrService": {
          "coding": [ {
            "system": "http://snomed.info/sct",
            "code": "410620009",
            "display": "Well child visit (procedure)"
          } ],
          "text": "Well child visit (procedure)"
        },
        "encounter": [ {
          "reference": "urn:uuid:fd0f4a40-24d2-87b3-5b4a-df1af3071cc8"
        } ]
      }, {
        "sequence": 2,
        "informationSequence": [ 1 ],
        "productOrService": {
          "coding": [ {
            "system": "http://hl7.org/fhir/sid/cvx",
            "code": "08",
            "display": "Hep B, adolescent or pediatric"
          } ],
          "text": "Hep B, adolescent or pediatric"
        },
        "net": {
          "value": 136.00,
          "currency": "USD"
        }
      } ],
      "total": {
        "value": 125.0,
        "currency": "USD"
      }
    },
    "request": {
      "method": "POST",
      "url": "Claim"
    }
  }, {
    "fullUrl": "urn:uuid:a48f104f-0188-9976-0e4e-6807b830b5e7",
    "resource": {
      "resourceType": "ExplanationOfBenefit",
      "id": "a48f104f-0188-9976-0e4e-6807b830b5e7",
      "contained": [ {
        "resourceType": "ServiceRequest",
        "id": "referral",
        "status": "completed",
        "intent": "order",
        "subject": {
          "reference": "urn:uuid:d9af187e-147c-0613-c2eb-0ded1271436c"
        },
        "requester": {
          "reference": "Practitioner?identifier=http://hl7.org/fhir/sid/us-npi|9999999649"
        },
        "performer": [ {
          "reference": "Practitioner?identifier=http://hl7.org/fhir/sid/us-npi|9999999649"
        } ]
      }, {
        "resourceType": "Coverage",
        "id": "coverage",
        "status": "active",
        "type": {
          "text": "National Health Service"
        },
        "beneficiary": {
          "reference": "urn:uuid:d9af187e-147c-0613-c2eb-0ded1271436c"
        },
        "payor": [ {
          "display": "National Health Service"
        } ]
      } ],
      "identifier": [ {
        "system": "https://bluebutton.cms.gov/resources/variables/clm_id",
        "value": "82eaeea3-ac4d-2f0f-c1d2-8775604f6552"
      }, {
        "system": "https://bluebutton.cms.gov/resources/identifier/claim-group",
        "value": "99999999999"
      } ],
      "status": "active",
      "type": {
        "coding": [ {
          "system": "http://terminology.hl7.org/CodeSystem/claim-type",
          "code": "institutional"
        } ]
      },
      "use": "claim",
      "patient": {
        "reference": "urn:uuid:d9af187e-147c-0613-c2eb-0ded1271436c"
      },
      "billablePeriod": {
        "start": "2020-11-23T07:39:41+01:00",
        "end": "2021-11-23T07:39:41+01:00"
      },
      "created": "2020-11-23T07:39:41+01:00",
      "insurer": {
        "display": "National Health Service"
      },
      "provider": {
        "reference": "Practitioner?identifier=http://hl7.org/fhir/sid/us-npi|9999999649"
      },
      "referral": {
        "reference": "#referral"
      },
      "claim": {
        "reference": "urn:uuid:82eaeea3-ac4d-2f0f-c1d2-8775604f6552"
      },
      "outcome": "complete",
      "careTeam": [ {
        "sequence": 1,
        "provider": {
          "reference": "Practitioner?identifier=http://hl7.org/fhir/sid/us-npi|9999999649"
        },
        "role": {
          "coding": [ {
            "system": "http://terminology.hl7.org/CodeSystem/claimcareteamrole",
            "code": "primary",
            "display": "Primary Care Practitioner"
          } ]
        }
      } ],
      "insurance": [ {
        "focal": true,
        "coverage": {
          "reference": "#coverage",
          "display": "National Health Service"
        }
      } ],
      "item": [ {
        "sequence": 1,
        "category": {
          "coding": [ {
            "system": "https://bluebutton.cms.gov/resources/variables/line_cms_type_srvc_cd",
            "code": "1",
            "display": "Medical care"
          } ]
        },
        "productOrService": {
          "coding": [ {
            "system": "http://snomed.info/sct",
            "code": "410620009",
            "display": "Well child visit (procedure)"
          } ],
          "text": "Well child visit (procedure)"
        },
        "servicedPeriod": {
          "start": "2020-11-23T07:24:41+01:00",
          "end": "2020-11-23T07:39:41+01:00"
        },
        "locationCodeableConcept": {
          "coding": [ {
            "system": "http://terminology.hl7.org/CodeSystem/ex-serviceplace",
            "code": "19",
            "display": "Off Campus-Outpatient Hospital"
          } ]
        },
        "encounter": [ {
          "reference": "urn:uuid:fd0f4a40-24d2-87b3-5b4a-df1af3071cc8"
        } ]
      }, {
        "sequence": 2,
        "informationSequence": [ 1 ],
        "category": {
          "coding": [ {
            "system": "https://bluebutton.cms.gov/resources/variables/line_cms_type_srvc_cd",
            "code": "1",
            "display": "Medical care"
          } ]
        },
        "productOrService": {
          "coding": [ {
            "system": "http://hl7.org/fhir/sid/cvx",
            "code": "08",
            "display": "Hep B, adolescent or pediatric"
          } ],
          "text": "Hep B, adolescent or pediatric"
        },
        "servicedPeriod": {
          "start": "2020-11-23T07:24:41+01:00",
          "end": "2020-11-23T07:39:41+01:00"
        },
        "locationCodeableConcept": {
          "coding": [ {
            "system": "http://terminology.hl7.org/CodeSystem/ex-serviceplace",
            "code": "19",
            "display": "Off Campus-Outpatient Hospital"
          } ]
        },
        "net": {
          "value": 136.00,
          "currency": "USD"
        },
        "adjudication": [ {
          "category": {
            "coding": [ {
              "system": "https://bluebutton.cms.gov/resources/codesystem/adjudication",
              "code": "https://bluebutton.cms.gov/resources/variables/line_coinsrnc_amt",
              "display": "Line Beneficiary Coinsurance Amount"
            } ]
          },
          "amount": {
            "value": 27.200000000000003,
            "currency": "USD"
          }
        }, {
          "category": {
            "coding": [ {
              "system": "https://bluebutton.cms.gov/resources/codesystem/adjudication",
              "code": "https://bluebutton.cms.gov/resources/variables/line_prvdr_pmt_amt",
              "display": "Line Provider Payment Amount"
            } ]
          },
          "amount": {
            "value": 108.80000000000001,
            "currency": "USD"
          }
        }, {
          "category": {
            "coding": [ {
              "system": "https://bluebutton.cms.gov/resources/codesystem/adjudication",
              "code": "https://bluebutton.cms.gov/resources/variables/line_sbmtd_chrg_amt",
              "display": "Line Submitted Charge Amount"
            } ]
          },
          "amount": {
            "value": 136.00,
            "currency": "USD"
          }
        }, {
          "category": {
            "coding": [ {
              "system": "https://bluebutton.cms.gov/resources/codesystem/adjudication",
              "code": "https://bluebutton.cms.gov/resources/variables/line_alowd_chrg_amt",
              "display": "Line Allowed Charge Amount"
            } ]
          },
          "amount": {
            "value": 136.00,
            "currency": "USD"
          }
        }, {
          "category": {
            "coding": [ {
              "system": "https://bluebutton.cms.gov/resources/codesystem/adjudication",
              "code": "https://bluebutton.cms.gov/resources/variables/line_bene_ptb_ddctbl_amt",
              "display": "Line Beneficiary Part B Deductible Amount"
            } ]
          },
          "amount": {
            "value": 0,
            "currency": "USD"
          }
        }, {
          "category": {
            "coding": [ {
              "system": "https://bluebutton.cms.gov/resources/codesystem/adjudication",
              "code": "https://bluebutton.cms.gov/resources/variables/line_prcsg_ind_cd",
              "display": "Line Processing Indicator Code"
            } ]
          }
        } ]
      } ],
      "total": [ {
        "category": {
          "coding": [ {
            "system": "http://terminology.hl7.org/CodeSystem/adjudication",
            "code": "submitted",
            "display": "Submitted Amount"
          } ],
          "text": "Submitted Amount"
        },
        "amount": {
          "value": 125.0,
          "currency": "USD"
        }
      } ],
      "payment": {
        "amount": {
          "value": 108.80000000000001,
          "currency": "USD"
        }
      }
    },
    "request": {
      "method": "POST",
      "url": "ExplanationOfBenefit"
    }
  }, {
    "fullUrl": "urn:uuid:8707160e-a9e7-061f-baa2-1c57d415a379",
    "resource": {
      "resourceType": "Encounter",
      "id": "8707160e-a9e7-061f-baa2-1c57d415a379",
      "status": "finished",
      "class": {
        "system": "http://terminology.hl7.org/CodeSystem/v3-ActCode",
        "code": "AMB"
      },
      "type": [ {
        "coding": [ {
          "system": "http://snomed.info/sct",
          "code": "410620009",
          "display": "Well child visit (procedure)"
        } ],
        "text": "Well child visit (procedure)"
      } ],
      "subject": {
        "reference": "urn:uuid:d9af187e-147c-0613-c2eb-0ded1271436c",
        "display": "Minda79 Lemke654"
      },
      "participant": [ {
        "type": [ {
          "coding": [ {
            "system": "http://terminology.hl7.org/CodeSystem/v3-ParticipationType",
            "code": "PPRF",
            "display": "primary performer"
          } ],
          "text": "primary performer"
        } ],
        "period": {
          "start": "2021-01-25T07:24:41+01:00",
          "end": "2021-01-25T07:39:41+01:00"
        },
        "individual": {
          "reference": "Practitioner?identifier=http://hl7.org/fhir/sid/us-npi|9999999649",
          "display": "Dr. Alix578 Lynch190"
        }
      } ],
      "period": {
        "start": "2021-01-25T07:24:41+01:00",
        "end": "2021-01-25T07:39:41+01:00"
      },
      "serviceProvider": {
        "reference": "Organization?identifier=https://github.com/synthetichealth/synthea|5117b3d6-41d4-35d0-8b1f-4990d5b796b9",
        "display": "Woodend Hospital"
      }
    },
    "request": {
      "method": "POST",
      "url": "Encounter"
    }
  }, {
    "fullUrl": "urn:uuid:3ca188ed-ee55-85e8-814d-c0e7a0dc42a4",
    "resource": {
      "resourceType": "Immunization",
      "id": "3ca188ed-ee55-85e8-814d-c0e7a0dc42a4",
      "status": "completed",
      "vaccineCode": {
        "coding": [ {
          "system": "http://hl7.org/fhir/sid/cvx",
          "code": "49",
          "display": "Hib (PRP-OMP)"
        } ],
        "text": "Hib (PRP-OMP)"
      },
      "patient": {
        "reference": "urn:uuid:d9af187e-147c-0613-c2eb-0ded1271436c"
      },
      "encounter": {
        "reference": "urn:uuid:8707160e-a9e7-061f-baa2-1c57d415a379"
      },
      "occurrenceDateTime": "2021-01-25T07:24:41+01:00",
      "primarySource": true
    },
    "request": {
      "method": "POST",
      "url": "Immunization"
    }
  }, {
    "fullUrl": "urn:uuid:9842c7c7-880e-3347-4418-5190c37389f8",
    "resource": {
      "resourceType": "Immunization",
      "id": "9842c7c7-880e-3347-4418-5190c37389f8",
      "status": "completed",
      "vaccineCode": {
        "coding": [ {
          "system": "http://hl7.org/fhir/sid/cvx",
          "code": "119",
          "display": "rotavirus, monovalent"
        } ],
        "text": "rotavirus, monovalent"
      },
      "patient": {
        "reference": "urn:uuid:d9af187e-147c-0613-c2eb-0ded1271436c"
      },
      "encounter": {
        "reference": "urn:uuid:8707160e-a9e7-061f-baa2-1c57d415a379"
      },
      "occurrenceDateTime": "2021-01-25T07:24:41+01:00",
      "primarySource": true
    },
    "request": {
      "method": "POST",
      "url": "Immunization"
    }
  }, {
    "fullUrl": "urn:uuid:95d20b1d-67e3-4b8f-a26c-83718f2556db",
    "resource": {
      "resourceType": "Immunization",
      "id": "95d20b1d-67e3-4b8f-a26c-83718f2556db",
      "status": "completed",
      "vaccineCode": {
        "coding": [ {
          "system": "http://hl7.org/fhir/sid/cvx",
          "code": "10",
          "display": "IPV"
        } ],
        "text": "IPV"
      },
      "patient": {
        "reference": "urn:uuid:d9af187e-147c-0613-c2eb-0ded1271436c"
      },
      "encounter": {
        "reference": "urn:uuid:8707160e-a9e7-061f-baa2-1c57d415a379"
      },
      "occurrenceDateTime": "2021-01-25T07:24:41+01:00",
      "primarySource": true
    },
    "request": {
      "method": "POST",
      "url": "Immunization"
    }
  }, {
    "fullUrl": "urn:uuid:f2525227-c44c-1872-4c54-ca23ab815cad",
    "resource": {
      "resourceType": "Immunization",
      "id": "f2525227-c44c-1872-4c54-ca23ab815cad",
      "status": "completed",
      "vaccineCode": {
        "coding": [ {
          "system": "http://hl7.org/fhir/sid/cvx",
          "code": "20",
          "display": "DTaP"
        } ],
        "text": "DTaP"
      },
      "patient": {
        "reference": "urn:uuid:d9af187e-147c-0613-c2eb-0ded1271436c"
      },
      "encounter": {
        "reference": "urn:uuid:8707160e-a9e7-061f-baa2-1c57d415a379"
      },
      "occurrenceDateTime": "2021-01-25T07:24:41+01:00",
      "primarySource": true
    },
    "request": {
      "method": "POST",
      "url": "Immunization"
    }
  }, {
    "fullUrl": "urn:uuid:90f48d30-5198-6dc6-1c15-fc321de5622d",
    "resource": {
      "resourceType": "Immunization",
      "id": "90f48d30-5198-6dc6-1c15-fc321de5622d",
      "status": "completed",
      "vaccineCode": {
        "coding": [ {
          "system": "http://hl7.org/fhir/sid/cvx",
          "code": "133",
          "display": "Pneumococcal conjugate PCV 13"
        } ],
        "text": "Pneumococcal conjugate PCV 13"
      },
      "patient": {
        "reference": "urn:uuid:d9af187e-147c-0613-c2eb-0ded1271436c"
      },
      "encounter": {
        "reference": "urn:uuid:8707160e-a9e7-061f-baa2-1c57d415a379"
      },
      "occurrenceDateTime": "2021-01-25T07:24:41+01:00",
      "primarySource": true
    },
    "request": {
      "method": "POST",
      "url": "Immunization"
    }
  }, {
    "fullUrl": "urn:uuid:4171991c-d2b7-bf8c-5c6b-4ac78381711b",
    "resource": {
      "resourceType": "Claim",
      "id": "4171991c-d2b7-bf8c-5c6b-4ac78381711b",
      "status": "active",
      "type": {
        "coding": [ {
          "system": "http://terminology.hl7.org/CodeSystem/claim-type",
          "code": "institutional"
        } ]
      },
      "use": "claim",
      "patient": {
        "reference": "urn:uuid:d9af187e-147c-0613-c2eb-0ded1271436c",
        "display": "Minda79 Lemke654"
      },
      "billablePeriod": {
        "start": "2021-01-25T07:24:41+01:00",
        "end": "2021-01-25T07:39:41+01:00"
      },
      "created": "2021-01-25T07:39:41+01:00",
      "provider": {
        "reference": "Organization?identifier=https://github.com/synthetichealth/synthea|5117b3d6-41d4-35d0-8b1f-4990d5b796b9",
        "display": "Woodend Hospital"
      },
      "priority": {
        "coding": [ {
          "system": "http://terminology.hl7.org/CodeSystem/processpriority",
          "code": "normal"
        } ]
      },
      "supportingInfo": [ {
        "sequence": 1,
        "category": {
          "coding": [ {
            "system": "http://terminology.hl7.org/CodeSystem/claiminformationcategory",
            "code": "info"
          } ]
        },
        "valueReference": {
          "reference": "urn:uuid:3ca188ed-ee55-85e8-814d-c0e7a0dc42a4"
        }
      }, {
        "sequence": 2,
        "category": {
          "coding": [ {
            "system": "http://terminology.hl7.org/CodeSystem/claiminformationcategory",
            "code": "info"
          } ]
        },
        "valueReference": {
          "reference": "urn:uuid:9842c7c7-880e-3347-4418-5190c37389f8"
        }
      }, {
        "sequence": 3,
        "category": {
          "coding": [ {
            "system": "http://terminology.hl7.org/CodeSystem/claiminformationcategory",
            "code": "info"
          } ]
        },
        "valueReference": {
          "reference": "urn:uuid:95d20b1d-67e3-4b8f-a26c-83718f2556db"
        }
      }, {
        "sequence": 4,
        "category": {
          "coding": [ {
            "system": "http://terminology.hl7.org/CodeSystem/claiminformationcategory",
            "code": "info"
          } ]
        },
        "valueReference": {
          "reference": "urn:uuid:f2525227-c44c-1872-4c54-ca23ab815cad"
        }
      }, {
        "sequence": 5,
        "category": {
          "coding": [ {
            "system": "http://terminology.hl7.org/CodeSystem/claiminformationcategory",
            "code": "info"
          } ]
        },
        "valueReference": {
          "reference": "urn:uuid:90f48d30-5198-6dc6-1c15-fc321de5622d"
        }
      } ],
      "insurance": [ {
        "sequence": 1,
        "focal": true,
        "coverage": {
          "display": "National Health Service"
        }
      } ],
      "item": [ {
        "sequence": 1,
        "productOrService": {
          "coding": [ {
            "system": "http://snomed.info/sct",
            "code": "410620009",
            "display": "Well child visit (procedure)"
          } ],
          "text": "Well child visit (procedure)"
        },
        "encounter": [ {
          "reference": "urn:uuid:8707160e-a9e7-061f-baa2-1c57d415a379"
        } ]
      }, {
        "sequence": 2,
        "informationSequence": [ 1 ],
        "productOrService": {
          "coding": [ {
            "system": "http://hl7.org/fhir/sid/cvx",
            "code": "49",
            "display": "Hib (PRP-OMP)"
          } ],
          "text": "Hib (PRP-OMP)"
        },
        "net": {
          "value": 136.00,
          "currency": "USD"
        }
      }, {
        "sequence": 3,
        "informationSequence": [ 2 ],
        "productOrService": {
          "coding": [ {
            "system": "http://hl7.org/fhir/sid/cvx",
            "code": "119",
            "display": "rotavirus, monovalent"
          } ],
          "text": "rotavirus, monovalent"
        },
        "net": {
          "value": 136.00,
          "currency": "USD"
        }
      }, {
        "sequence": 4,
        "informationSequence": [ 3 ],
        "productOrService": {
          "coding": [ {
            "system": "http://hl7.org/fhir/sid/cvx",
            "code": "10",
            "display": "IPV"
          } ],
          "text": "IPV"
        },
        "net": {
          "value": 136.00,
          "currency": "USD"
        }
      }, {
        "sequence": 5,
        "informationSequence": [ 4 ],
        "productOrService": {
          "coding": [ {
            "system": "http://hl7.org/fhir/sid/cvx",
            "code": "20",
            "display": "DTaP"
          } ],
          "text": "DTaP"
        },
        "net": {
          "value": 136.00,
          "currency": "USD"
        }
      }, {
        "sequence": 6,
        "informationSequence": [ 5 ],
        "productOrService": {
          "coding": [ {
            "system": "http://hl7.org/fhir/sid/cvx",
            "code": "133",
            "display": "Pneumococcal conjugate PCV 13"
          } ],
          "text": "Pneumococcal conjugate PCV 13"
        },
        "net": {
          "value": 136.00,
          "currency": "USD"
        }
      } ],
      "total": {
        "value": 125.0,
        "currency": "USD"
      }
    },
    "request": {
      "method": "POST",
      "url": "Claim"
    }
  }, {
    "fullUrl": "urn:uuid:59cfe04d-3c4d-142d-f25d-80a8e57cdc1d",
    "resource": {
      "resourceType": "ExplanationOfBenefit",
      "id": "59cfe04d-3c4d-142d-f25d-80a8e57cdc1d",
      "contained": [ {
        "resourceType": "ServiceRequest",
        "id": "referral",
        "status": "completed",
        "intent": "order",
        "subject": {
          "reference": "urn:uuid:d9af187e-147c-0613-c2eb-0ded1271436c"
        },
        "requester": {
          "reference": "Practitioner?identifier=http://hl7.org/fhir/sid/us-npi|9999999649"
        },
        "performer": [ {
          "reference": "Practitioner?identifier=http://hl7.org/fhir/sid/us-npi|9999999649"
        } ]
      }, {
        "resourceType": "Coverage",
        "id": "coverage",
        "status": "active",
        "type": {
          "text": "National Health Service"
        },
        "beneficiary": {
          "reference": "urn:uuid:d9af187e-147c-0613-c2eb-0ded1271436c"
        },
        "payor": [ {
          "display": "National Health Service"
        } ]
      } ],
      "identifier": [ {
        "system": "https://bluebutton.cms.gov/resources/variables/clm_id",
        "value": "4171991c-d2b7-bf8c-5c6b-4ac78381711b"
      }, {
        "system": "https://bluebutton.cms.gov/resources/identifier/claim-group",
        "value": "99999999999"
      } ],
      "status": "active",
      "type": {
        "coding": [ {
          "system": "http://terminology.hl7.org/CodeSystem/claim-type",
          "code": "institutional"
        } ]
      },
      "use": "claim",
      "patient": {
        "reference": "urn:uuid:d9af187e-147c-0613-c2eb-0ded1271436c"
      },
      "billablePeriod": {
        "start": "2021-01-25T07:39:41+01:00",
        "end": "2022-01-25T07:39:41+01:00"
      },
      "created": "2021-01-25T07:39:41+01:00",
      "insurer": {
        "display": "National Health Service"
      },
      "provider": {
        "reference": "Practitioner?identifier=http://hl7.org/fhir/sid/us-npi|9999999649"
      },
      "referral": {
        "reference": "#referral"
      },
      "claim": {
        "reference": "urn:uuid:4171991c-d2b7-bf8c-5c6b-4ac78381711b"
      },
      "outcome": "complete",
      "careTeam": [ {
        "sequence": 1,
        "provider": {
          "reference": "Practitioner?identifier=http://hl7.org/fhir/sid/us-npi|9999999649"
        },
        "role": {
          "coding": [ {
            "system": "http://terminology.hl7.org/CodeSystem/claimcareteamrole",
            "code": "primary",
            "display": "Primary Care Practitioner"
          } ]
        }
      } ],
      "insurance": [ {
        "focal": true,
        "coverage": {
          "reference": "#coverage",
          "display": "National Health Service"
        }
      } ],
      "item": [ {
        "sequence": 1,
        "category": {
          "coding": [ {
            "system": "https://bluebutton.cms.gov/resources/variables/line_cms_type_srvc_cd",
            "code": "1",
            "display": "Medical care"
          } ]
        },
        "productOrService": {
          "coding": [ {
            "system": "http://snomed.info/sct",
            "code": "410620009",
            "display": "Well child visit (procedure)"
          } ],
          "text": "Well child visit (procedure)"
        },
        "servicedPeriod": {
          "start": "2021-01-25T07:24:41+01:00",
          "end": "2021-01-25T07:39:41+01:00"
        },
        "locationCodeableConcept": {
          "coding": [ {
            "system": "http://terminology.hl7.org/CodeSystem/ex-serviceplace",
            "code": "19",
            "display": "Off Campus-Outpatient Hospital"
          } ]
        },
        "encounter": [ {
          "reference": "urn:uuid:8707160e-a9e7-061f-baa2-1c57d415a379"
        } ]
      }, {
        "sequence": 2,
        "informationSequence": [ 1 ],
        "category": {
          "coding": [ {
            "system": "https://bluebutton.cms.gov/resources/variables/line_cms_type_srvc_cd",
            "code": "1",
            "display": "Medical care"
          } ]
        },
        "productOrService": {
          "coding": [ {
            "system": "http://hl7.org/fhir/sid/cvx",
            "code": "49",
            "display": "Hib (PRP-OMP)"
          } ],
          "text": "Hib (PRP-OMP)"
        },
        "servicedPeriod": {
          "start": "2021-01-25T07:24:41+01:00",
          "end": "2021-01-25T07:39:41+01:00"
        },
        "locationCodeableConcept": {
          "coding": [ {
            "system": "http://terminology.hl7.org/CodeSystem/ex-serviceplace",
            "code": "19",
            "display": "Off Campus-Outpatient Hospital"
          } ]
        },
        "net": {
          "value": 136.00,
          "currency": "USD"
        },
        "adjudication": [ {
          "category": {
            "coding": [ {
              "system": "https://bluebutton.cms.gov/resources/codesystem/adjudication",
              "code": "https://bluebutton.cms.gov/resources/variables/line_coinsrnc_amt",
              "display": "Line Beneficiary Coinsurance Amount"
            } ]
          },
          "amount": {
            "value": 27.200000000000003,
            "currency": "USD"
          }
        }, {
          "category": {
            "coding": [ {
              "system": "https://bluebutton.cms.gov/resources/codesystem/adjudication",
              "code": "https://bluebutton.cms.gov/resources/variables/line_prvdr_pmt_amt",
              "display": "Line Provider Payment Amount"
            } ]
          },
          "amount": {
            "value": 108.80000000000001,
            "currency": "USD"
          }
        }, {
          "category": {
            "coding": [ {
              "system": "https://bluebutton.cms.gov/resources/codesystem/adjudication",
              "code": "https://bluebutton.cms.gov/resources/variables/line_sbmtd_chrg_amt",
              "display": "Line Submitted Charge Amount"
            } ]
          },
          "amount": {
            "value": 136.00,
            "currency": "USD"
          }
        }, {
          "category": {
            "coding": [ {
              "system": "https://bluebutton.cms.gov/resources/codesystem/adjudication",
              "code": "https://bluebutton.cms.gov/resources/variables/line_alowd_chrg_amt",
              "display": "Line Allowed Charge Amount"
            } ]
          },
          "amount": {
            "value": 136.00,
            "currency": "USD"
          }
        }, {
          "category": {
            "coding": [ {
              "system": "https://bluebutton.cms.gov/resources/codesystem/adjudication",
              "code": "https://bluebutton.cms.gov/resources/variables/line_bene_ptb_ddctbl_amt",
              "display": "Line Beneficiary Part B Deductible Amount"
            } ]
          },
          "amount": {
            "value": 0,
            "currency": "USD"
          }
        }, {
          "category": {
            "coding": [ {
              "system": "https://bluebutton.cms.gov/resources/codesystem/adjudication",
              "code": "https://bluebutton.cms.gov/resources/variables/line_prcsg_ind_cd",
              "display": "Line Processing Indicator Code"
            } ]
          }
        } ]
      }, {
        "sequence": 3,
        "informationSequence": [ 2 ],
        "category": {
          "coding": [ {
            "system": "https://bluebutton.cms.gov/resources/variables/line_cms_type_srvc_cd",
            "code": "1",
            "display": "Medical care"
          } ]
        },
        "productOrService": {
          "coding": [ {
            "system": "http://hl7.org/fhir/sid/cvx",
            "code": "119",
            "display": "rotavirus, monovalent"
          } ],
          "text": "rotavirus, monovalent"
        },
        "servicedPeriod": {
          "start": "2021-01-25T07:24:41+01:00",
          "end": "2021-01-25T07:39:41+01:00"
        },
        "locationCodeableConcept": {
          "coding": [ {
            "system": "http://terminology.hl7.org/CodeSystem/ex-serviceplace",
            "code": "19",
            "display": "Off Campus-Outpatient Hospital"
          } ]
        },
        "net": {
          "value": 136.00,
          "currency": "USD"
        },
        "adjudication": [ {
          "category": {
            "coding": [ {
              "system": "https://bluebutton.cms.gov/resources/codesystem/adjudication",
              "code": "https://bluebutton.cms.gov/resources/variables/line_coinsrnc_amt",
              "display": "Line Beneficiary Coinsurance Amount"
            } ]
          },
          "amount": {
            "value": 27.200000000000003,
            "currency": "USD"
          }
        }, {
          "category": {
            "coding": [ {
              "system": "https://bluebutton.cms.gov/resources/codesystem/adjudication",
              "code": "https://bluebutton.cms.gov/resources/variables/line_prvdr_pmt_amt",
              "display": "Line Provider Payment Amount"
            } ]
          },
          "amount": {
            "value": 108.80000000000001,
            "currency": "USD"
          }
        }, {
          "category": {
            "coding": [ {
              "system": "https://bluebutton.cms.gov/resources/codesystem/adjudication",
              "code": "https://bluebutton.cms.gov/resources/variables/line_sbmtd_chrg_amt",
              "display": "Line Submitted Charge Amount"
            } ]
          },
          "amount": {
            "value": 136.00,
            "currency": "USD"
          }
        }, {
          "category": {
            "coding": [ {
              "system": "https://bluebutton.cms.gov/resources/codesystem/adjudication",
              "code": "https://bluebutton.cms.gov/resources/variables/line_alowd_chrg_amt",
              "display": "Line Allowed Charge Amount"
            } ]
          },
          "amount": {
            "value": 136.00,
            "currency": "USD"
          }
        }, {
          "category": {
            "coding": [ {
              "system": "https://bluebutton.cms.gov/resources/codesystem/adjudication",
              "code": "https://bluebutton.cms.gov/resources/variables/line_bene_ptb_ddctbl_amt",
              "display": "Line Beneficiary Part B Deductible Amount"
            } ]
          },
          "amount": {
            "value": 0,
            "currency": "USD"
          }
        }, {
          "category": {
            "coding": [ {
              "system": "https://bluebutton.cms.gov/resources/codesystem/adjudication",
              "code": "https://bluebutton.cms.gov/resources/variables/line_prcsg_ind_cd",
              "display": "Line Processing Indicator Code"
            } ]
          }
        } ]
      }, {
        "sequence": 4,
        "informationSequence": [ 3 ],
        "category": {
          "coding": [ {
            "system": "https://bluebutton.cms.gov/resources/variables/line_cms_type_srvc_cd",
            "code": "1",
            "display": "Medical care"
          } ]
        },
        "productOrService": {
          "coding": [ {
            "system": "http://hl7.org/fhir/sid/cvx",
            "code": "10",
            "display": "IPV"
          } ],
          "text": "IPV"
        },
        "servicedPeriod": {
          "start": "2021-01-25T07:24:41+01:00",
          "end": "2021-01-25T07:39:41+01:00"
        },
        "locationCodeableConcept": {
          "coding": [ {
            "system": "http://terminology.hl7.org/CodeSystem/ex-serviceplace",
            "code": "19",
            "display": "Off Campus-Outpatient Hospital"
          } ]
        },
        "net": {
          "value": 136.00,
          "currency": "USD"
        },
        "adjudication": [ {
          "category": {
            "coding": [ {
              "system": "https://bluebutton.cms.gov/resources/codesystem/adjudication",
              "code": "https://bluebutton.cms.gov/resources/variables/line_coinsrnc_amt",
              "display": "Line Beneficiary Coinsurance Amount"
            } ]
          },
          "amount": {
            "value": 27.200000000000003,
            "currency": "USD"
          }
        }, {
          "category": {
            "coding": [ {
              "system": "https://bluebutton.cms.gov/resources/codesystem/adjudication",
              "code": "https://bluebutton.cms.gov/resources/variables/line_prvdr_pmt_amt",
              "display": "Line Provider Payment Amount"
            } ]
          },
          "amount": {
            "value": 108.80000000000001,
            "currency": "USD"
          }
        }, {
          "category": {
            "coding": [ {
              "system": "https://bluebutton.cms.gov/resources/codesystem/adjudication",
              "code": "https://bluebutton.cms.gov/resources/variables/line_sbmtd_chrg_amt",
              "display": "Line Submitted Charge Amount"
            } ]
          },
          "amount": {
            "value": 136.00,
            "currency": "USD"
          }
        }, {
          "category": {
            "coding": [ {
              "system": "https://bluebutton.cms.gov/resources/codesystem/adjudication",
              "code": "https://bluebutton.cms.gov/resources/variables/line_alowd_chrg_amt",
              "display": "Line Allowed Charge Amount"
            } ]
          },
          "amount": {
            "value": 136.00,
            "currency": "USD"
          }
        }, {
          "category": {
            "coding": [ {
              "system": "https://bluebutton.cms.gov/resources/codesystem/adjudication",
              "code": "https://bluebutton.cms.gov/resources/variables/line_bene_ptb_ddctbl_amt",
              "display": "Line Beneficiary Part B Deductible Amount"
            } ]
          },
          "amount": {
            "value": 0,
            "currency": "USD"
          }
        }, {
          "category": {
            "coding": [ {
              "system": "https://bluebutton.cms.gov/resources/codesystem/adjudication",
              "code": "https://bluebutton.cms.gov/resources/variables/line_prcsg_ind_cd",
              "display": "Line Processing Indicator Code"
            } ]
          }
        } ]
      }, {
        "sequence": 5,
        "informationSequence": [ 4 ],
        "category": {
          "coding": [ {
            "system": "https://bluebutton.cms.gov/resources/variables/line_cms_type_srvc_cd",
            "code": "1",
            "display": "Medical care"
          } ]
        },
        "productOrService": {
          "coding": [ {
            "system": "http://hl7.org/fhir/sid/cvx",
            "code": "20",
            "display": "DTaP"
          } ],
          "text": "DTaP"
        },
        "servicedPeriod": {
          "start": "2021-01-25T07:24:41+01:00",
          "end": "2021-01-25T07:39:41+01:00"
        },
        "locationCodeableConcept": {
          "coding": [ {
            "system": "http://terminology.hl7.org/CodeSystem/ex-serviceplace",
            "code": "19",
            "display": "Off Campus-Outpatient Hospital"
          } ]
        },
        "net": {
          "value": 136.00,
          "currency": "USD"
        },
        "adjudication": [ {
          "category": {
            "coding": [ {
              "system": "https://bluebutton.cms.gov/resources/codesystem/adjudication",
              "code": "https://bluebutton.cms.gov/resources/variables/line_coinsrnc_amt",
              "display": "Line Beneficiary Coinsurance Amount"
            } ]
          },
          "amount": {
            "value": 27.200000000000003,
            "currency": "USD"
          }
        }, {
          "category": {
            "coding": [ {
              "system": "https://bluebutton.cms.gov/resources/codesystem/adjudication",
              "code": "https://bluebutton.cms.gov/resources/variables/line_prvdr_pmt_amt",
              "display": "Line Provider Payment Amount"
            } ]
          },
          "amount": {
            "value": 108.80000000000001,
            "currency": "USD"
          }
        }, {
          "category": {
            "coding": [ {
              "system": "https://bluebutton.cms.gov/resources/codesystem/adjudication",
              "code": "https://bluebutton.cms.gov/resources/variables/line_sbmtd_chrg_amt",
              "display": "Line Submitted Charge Amount"
            } ]
          },
          "amount": {
            "value": 136.00,
            "currency": "USD"
          }
        }, {
          "category": {
            "coding": [ {
              "system": "https://bluebutton.cms.gov/resources/codesystem/adjudication",
              "code": "https://bluebutton.cms.gov/resources/variables/line_alowd_chrg_amt",
              "display": "Line Allowed Charge Amount"
            } ]
          },
          "amount": {
            "value": 136.00,
            "currency": "USD"
          }
        }, {
          "category": {
            "coding": [ {
              "system": "https://bluebutton.cms.gov/resources/codesystem/adjudication",
              "code": "https://bluebutton.cms.gov/resources/variables/line_bene_ptb_ddctbl_amt",
              "display": "Line Beneficiary Part B Deductible Amount"
            } ]
          },
          "amount": {
            "value": 0,
            "currency": "USD"
          }
        }, {
          "category": {
            "coding": [ {
              "system": "https://bluebutton.cms.gov/resources/codesystem/adjudication",
              "code": "https://bluebutton.cms.gov/resources/variables/line_prcsg_ind_cd",
              "display": "Line Processing Indicator Code"
            } ]
          }
        } ]
      }, {
        "sequence": 6,
        "informationSequence": [ 5 ],
        "category": {
          "coding": [ {
            "system": "https://bluebutton.cms.gov/resources/variables/line_cms_type_srvc_cd",
            "code": "1",
            "display": "Medical care"
          } ]
        },
        "productOrService": {
          "coding": [ {
            "system": "http://hl7.org/fhir/sid/cvx",
            "code": "133",
            "display": "Pneumococcal conjugate PCV 13"
          } ],
          "text": "Pneumococcal conjugate PCV 13"
        },
        "servicedPeriod": {
          "start": "2021-01-25T07:24:41+01:00",
          "end": "2021-01-25T07:39:41+01:00"
        },
        "locationCodeableConcept": {
          "coding": [ {
            "system": "http://terminology.hl7.org/CodeSystem/ex-serviceplace",
            "code": "19",
            "display": "Off Campus-Outpatient Hospital"
          } ]
        },
        "net": {
          "value": 136.00,
          "currency": "USD"
        },
        "adjudication": [ {
          "category": {
            "coding": [ {
              "system": "https://bluebutton.cms.gov/resources/codesystem/adjudication",
              "code": "https://bluebutton.cms.gov/resources/variables/line_coinsrnc_amt",
              "display": "Line Beneficiary Coinsurance Amount"
            } ]
          },
          "amount": {
            "value": 27.200000000000003,
            "currency": "USD"
          }
        }, {
          "category": {
            "coding": [ {
              "system": "https://bluebutton.cms.gov/resources/codesystem/adjudication",
              "code": "https://bluebutton.cms.gov/resources/variables/line_prvdr_pmt_amt",
              "display": "Line Provider Payment Amount"
            } ]
          },
          "amount": {
            "value": 108.80000000000001,
            "currency": "USD"
          }
        }, {
          "category": {
            "coding": [ {
              "system": "https://bluebutton.cms.gov/resources/codesystem/adjudication",
              "code": "https://bluebutton.cms.gov/resources/variables/line_sbmtd_chrg_amt",
              "display": "Line Submitted Charge Amount"
            } ]
          },
          "amount": {
            "value": 136.00,
            "currency": "USD"
          }
        }, {
          "category": {
            "coding": [ {
              "system": "https://bluebutton.cms.gov/resources/codesystem/adjudication",
              "code": "https://bluebutton.cms.gov/resources/variables/line_alowd_chrg_amt",
              "display": "Line Allowed Charge Amount"
            } ]
          },
          "amount": {
            "value": 136.00,
            "currency": "USD"
          }
        }, {
          "category": {
            "coding": [ {
              "system": "https://bluebutton.cms.gov/resources/codesystem/adjudication",
              "code": "https://bluebutton.cms.gov/resources/variables/line_bene_ptb_ddctbl_amt",
              "display": "Line Beneficiary Part B Deductible Amount"
            } ]
          },
          "amount": {
            "value": 0,
            "currency": "USD"
          }
        }, {
          "category": {
            "coding": [ {
              "system": "https://bluebutton.cms.gov/resources/codesystem/adjudication",
              "code": "https://bluebutton.cms.gov/resources/variables/line_prcsg_ind_cd",
              "display": "Line Processing Indicator Code"
            } ]
          }
        } ]
      } ],
      "total": [ {
        "category": {
          "coding": [ {
            "system": "http://terminology.hl7.org/CodeSystem/adjudication",
            "code": "submitted",
            "display": "Submitted Amount"
          } ],
          "text": "Submitted Amount"
        },
        "amount": {
          "value": 125.0,
          "currency": "USD"
        }
      } ],
      "payment": {
        "amount": {
          "value": 544.0,
          "currency": "USD"
        }
      }
    },
    "request": {
      "method": "POST",
      "url": "ExplanationOfBenefit"
    }
  } ]
}
